mdb/__init__.py
mdb/async_client.py
mdb/async_connection.py
mdb/backend.py
mdb/debug_client.py
mdb/exchange_server.py
mdb/mdb.py
mdb/mdb_attach.py
mdb/mdb_client.py
mdb/mdb_launch.py
mdb/mdb_shell.py
mdb/mdb_wrapper.py
mdb/messages.py
mdb/utils.py
mdb/plugins/cuda-gdb.py
mdb/plugins/gdb.py
mdb/plugins/lldb.py
mdb/plugins/rocmgdb.py
mdb/plugins/rust-gdb.py
mdb/plugins/rust-lldb.py
mdb/plugins/vgdb.py
mdb_debugger-1.0.5.dist-info/licenses/LICENSE
mdb_debugger-1.0.5.dist-info/METADATA
mdb_debugger-1.0.5.dist-info/WHEEL
mdb_debugger-1.0.5.dist-info/entry_points.txt
mdb_debugger-1.0.5.dist-info/top_level.txt
mdb_debugger-1.0.5.dist-info/RECORD
