Metadata-Version: 2.4
Name: mdb_debugger
Version: 1.0.5
Author-email: Tom Meltzer <tdm39@cam.ac.uk>
Maintainer-email: Tom Meltzer <tdm39@cam.ac.uk>
License: MIT License
Project-URL: Documentation, https://mdb.readthedocs.io/en/latest/
Project-URL: Repository, https://github.com/TomMelt/mdb
Project-URL: Issues, https://github.com/TomMelt/mdb/issues
Requires-Python: >=3.10
License-File: LICENSE
Requires-Dist: click==8.1.7
Requires-Dist: matplotlib==3.8.3
Requires-Dist: numpy==1.26.4
Requires-Dist: pexpect==4.9.0
Requires-Dist: typing_extensions==4.10.0
Provides-Extra: termgraph
Requires-Dist: termgraph==0.5.3; extra == "termgraph"
Provides-Extra: develop
Requires-Dist: black==24.3.0; extra == "develop"
Requires-Dist: flake8==7.0.0; extra == "develop"
Requires-Dist: mypy==1.9.0; extra == "develop"
Requires-Dist: types-setuptools==69.2.0.20240317; extra == "develop"
Requires-Dist: pytest==8.1.1; extra == "develop"
Requires-Dist: pytest-cov==4.1.0; extra == "develop"
Provides-Extra: docs
Requires-Dist: sphinx; extra == "docs"
Requires-Dist: sphinx_click; extra == "docs"
Requires-Dist: sphinx_rtd_theme; extra == "docs"
Dynamic: license-file
